setup.py
pyHTMLParser/Parser.py
pyHTMLParser/ParserUtils.py
pyHTMLParser/Query.py
pyHTMLParser/__init__.py
pyHTMLParser/pyNode.py
pyHTMLParser.egg-info/PKG-INFO
pyHTMLParser.egg-info/SOURCES.txt
pyHTMLParser.egg-info/dependency_links.txt
pyHTMLParser.egg-info/top_level.txt