Metadata-Version: 1.1
Name: pyHTMLParser
Version: 2.0.0
Summary: A simple html parser that constructs DOM tree.
Home-page: http://ishibashijun.github.io/pyHTMLParser/
Author: Jun Ishibashi
Author-email: ishibashijun@gmail.com
License: MIT
Keywords: parse,html,jquery,parser,tree,DOM
Platform: UNKNOWN
Classifier: Development Status :: 5 - Production/Stable
Classifier: License :: OSI Approved :: MIT License
Classifier: Programming Language :: Python :: 3
Classifier: Topic :: Internet :: WWW/HTTP
Classifier: Topic :: Text Processing :: Markup :: HTML
